{
    "$schema": "https://raw.githubusercontent.com/Cog-Creators/Red-DiscordBot/V3/develop/schema/red_cog.schema.json",
    "name": "FiveMStatus",
    "author": [
        "Taako"
    ],
    "version": "1.2.0",
    "description": "A Red DiscordBot cog that posts and refreshes a FiveM server status panel with live player counts, connect command, restart countdowns, uptime tracking, images, Join Server buttons, and link buttons.",
    "install_msg": "fivemstatus loaded. Use `[p]fivem setup <ip:port|cfx_code> [#channel]` to post a live FiveM status panel.",
    "short": "Live FiveM server status panel.",
    "tags": [
        "fivem",
        "gta",
        "status",
        "roleplay",
        "utility"
    ],
    "requirements": [
        "aiohttp"
    ],
    "min_bot_version": "3.5.0",
    "min_python_version": [
        3,
        9,
        0
    ],
    "hidden": false,
    "disabled": false,
    "type": "COG",
    "end_user_data_statement": "This cog stores per-guild FiveM status configuration, including server endpoints, channel IDs, message IDs, display text, image URLs, button URLs, restart schedule, and the timestamp when the configured server was first observed online. It does not store FiveM player records or Discord end user data."
}
